{
"meta":{"test_sets":[],"test_metrics":[],"learn_metrics":[{"best_value":"Min","name":"Logloss"}],"launch_mode":"Train","parameters":"","iteration_count":500,"learn_sets":["learn"],"name":"experiment"},
"iterations":[
{"learn":[0.5890848769],"iteration":0,"passed_time":0.0123314202,"remaining_time":6.153378678},
{"learn":[0.5053692965],"iteration":1,"passed_time":0.02067679506,"remaining_time":5.14852197},
{"learn":[0.4427979358],"iteration":2,"passed_time":0.02975007205,"remaining_time":4.928595269},
{"learn":[0.399888109],"iteration":3,"passed_time":0.03807003075,"remaining_time":4.720683813},
{"learn":[0.3652979787],"iteration":4,"passed_time":0.0458410421,"remaining_time":4.538263168},
{"learn":[0.3380726603],"iteration":5,"passed_time":0.05390229764,"remaining_time":4.437955839},
{"learn":[0.3220897955],"iteration":6,"passed_time":0.06285232709,"remaining_time":4.426599608},
{"learn":[0.3075830506],"iteration":7,"passed_time":0.09490306149,"remaining_time":5.836538281},
{"learn":[0.2980190164],"iteration":8,"passed_time":0.1078765938,"remaining_time":5.885267509},
{"learn":[0.290076109],"iteration":9,"passed_time":0.1209586657,"remaining_time":5.92697462},
{"learn":[0.2831324258],"iteration":10,"passed_time":0.128265353,"remaining_time":5.701977965},
{"learn":[0.2767152993],"iteration":11,"passed_time":0.1359736573,"remaining_time":5.529595395},
{"learn":[0.270631198],"iteration":12,"passed_time":0.1433314269,"remaining_time":5.36941576},
{"learn":[0.2648494856],"iteration":13,"passed_time":0.1505165749,"remaining_time":5.225075387},
{"learn":[0.2607538202],"iteration":14,"passed_time":0.1575889752,"remaining_time":5.095376866},
{"learn":[0.2560317857],"iteration":15,"passed_time":0.1646457509,"remaining_time":4.980533963},
{"learn":[0.2511538901],"iteration":16,"passed_time":0.1722385991,"remaining_time":4.893602551},
{"learn":[0.246958364],"iteration":17,"passed_time":0.1795397032,"remaining_time":4.807674274},
{"learn":[0.2446193185],"iteration":18,"passed_time":0.1867841,"remaining_time":4.728586954},
{"learn":[0.2402560372],"iteration":19,"passed_time":0.1941206617,"remaining_time":4.658895882},
{"learn":[0.2360359678],"iteration":20,"passed_time":0.2018956313,"remaining_time":4.60514321},
{"learn":[0.2338663801],"iteration":21,"passed_time":0.2089393239,"remaining_time":4.539681674},
{"learn":[0.2308532366],"iteration":22,"passed_time":0.2167905836,"remaining_time":4.496048191},
{"learn":[0.2286366622],"iteration":23,"passed_time":0.2240799796,"remaining_time":4.444252929},
{"learn":[0.2245770783],"iteration":24,"passed_time":0.2339699903,"remaining_time":4.445429815},
{"learn":[0.2220774703],"iteration":25,"passed_time":0.242954019,"remaining_time":4.429238655},
{"learn":[0.2184932068],"iteration":26,"passed_time":0.2524385378,"remaining_time":4.422349199},
{"learn":[0.2174267398],"iteration":27,"passed_time":0.260683623,"remaining_time":4.394381073},
{"learn":[0.2143285912],"iteration":28,"passed_time":0.2693044507,"remaining_time":4.373875734},
{"learn":[0.212539242],"iteration":29,"passed_time":0.2769276317,"remaining_time":4.338532896},
{"learn":[0.2108982092],"iteration":30,"passed_time":0.2897243759,"remaining_time":4.383249429},
{"learn":[0.2095686016],"iteration":31,"passed_time":0.3041206715,"remaining_time":4.44776482},
{"learn":[0.2080996094],"iteration":32,"passed_time":0.3568216181,"remaining_time":5.049566535},
{"learn":[0.2054010206],"iteration":33,"passed_time":0.3700189794,"remaining_time":5.071436599},
{"learn":[0.2026414385],"iteration":34,"passed_time":0.3840517822,"remaining_time":5.102402249},
{"learn":[0.2014825384],"iteration":35,"passed_time":0.3979796705,"remaining_time":5.129515753},
{"learn":[0.2004772091],"iteration":36,"passed_time":0.4085558341,"remaining_time":5.112468951},
{"learn":[0.1982045946],"iteration":37,"passed_time":0.4190264582,"remaining_time":5.09447957},
{"learn":[0.1948884596],"iteration":38,"passed_time":0.4314092107,"remaining_time":5.099478106},
{"learn":[0.1937011763],"iteration":39,"passed_time":0.4443915762,"remaining_time":5.110503126},
{"learn":[0.1922002168],"iteration":40,"passed_time":0.4598120596,"remaining_time":5.147652082},
{"learn":[0.191294806],"iteration":41,"passed_time":0.4731938338,"remaining_time":5.160066093},
{"learn":[0.1903063471],"iteration":42,"passed_time":0.4835255857,"remaining_time":5.138864945},
{"learn":[0.187009873],"iteration":43,"passed_time":0.4921087058,"remaining_time":5.100035678},
{"learn":[0.1857770873],"iteration":44,"passed_time":0.4999005917,"remaining_time":5.054550427},
{"learn":[0.1848909461],"iteration":45,"passed_time":0.5067057474,"remaining_time":5.00096542},
{"learn":[0.1835078169],"iteration":46,"passed_time":0.5346808966,"remaining_time":5.153413748},
{"learn":[0.1818495626],"iteration":47,"passed_time":0.5490341513,"remaining_time":5.170071592},
{"learn":[0.1802027572],"iteration":48,"passed_time":0.5610324532,"remaining_time":5.163788498},
{"learn":[0.1783262397],"iteration":49,"passed_time":0.5685114287,"remaining_time":5.116602858},
{"learn":[0.176292049],"iteration":50,"passed_time":0.5755794541,"remaining_time":5.06735637},
{"learn":[0.1743335218],"iteration":51,"passed_time":0.5827778936,"remaining_time":5.020855698},
{"learn":[0.1738445051],"iteration":52,"passed_time":0.5895110507,"remaining_time":4.971913956},
{"learn":[0.1729202669],"iteration":53,"passed_time":0.5964549119,"remaining_time":4.926275754},
{"learn":[0.1709330906],"iteration":54,"passed_time":0.6037375996,"remaining_time":4.884786033},
{"learn":[0.1700298115],"iteration":55,"passed_time":0.6109892047,"remaining_time":4.844271552},
{"learn":[0.1691791222],"iteration":56,"passed_time":0.6183121417,"remaining_time":4.805478575},
{"learn":[0.1680086617],"iteration":57,"passed_time":0.6257280768,"remaining_time":4.768479482},
{"learn":[0.1670414103],"iteration":58,"passed_time":0.6337521247,"remaining_time":4.737028593},
{"learn":[0.1659964671],"iteration":59,"passed_time":0.6410582704,"remaining_time":4.701093983},
{"learn":[0.1638340583],"iteration":60,"passed_time":0.6498491363,"remaining_time":4.676783129},
{"learn":[0.1618785791],"iteration":61,"passed_time":0.6579560576,"remaining_time":4.648141181},
{"learn":[0.161512386],"iteration":62,"passed_time":0.6654297416,"remaining_time":4.615758684},
{"learn":[0.1606840427],"iteration":63,"passed_time":0.6726893882,"remaining_time":4.582696457},
{"learn":[0.1603572374],"iteration":64,"passed_time":0.6806394376,"remaining_time":4.555048544},
{"learn":[0.1595152203],"iteration":65,"passed_time":0.6882277442,"remaining_time":4.525618803},
{"learn":[0.1581584864],"iteration":66,"passed_time":0.6963547901,"remaining_time":4.500322748},
{"learn":[0.1573589226],"iteration":67,"passed_time":0.7131427046,"remaining_time":4.530553653},
{"learn":[0.1559596219],"iteration":68,"passed_time":0.7363969898,"remaining_time":4.599813081},
{"learn":[0.1547331073],"iteration":69,"passed_time":0.7487733258,"remaining_time":4.599607573},
{"learn":[0.1530950105],"iteration":70,"passed_time":0.7563715489,"remaining_time":4.570188655},
{"learn":[0.1525705369],"iteration":71,"passed_time":0.7634409076,"remaining_time":4.538232062},
{"learn":[0.1516976892],"iteration":72,"passed_time":0.770627764,"remaining_time":4.507644592},
{"learn":[0.1505733887],"iteration":73,"passed_time":0.7780130747,"remaining_time":4.478832025},
{"learn":[0.1492905817],"iteration":74,"passed_time":0.7850714753,"remaining_time":4.44873836},
{"learn":[0.1487630848],"iteration":75,"passed_time":0.7918407983,"remaining_time":4.417638138},
{"learn":[0.1478121357],"iteration":76,"passed_time":0.7989441147,"remaining_time":4.389004682},
{"learn":[0.147045784],"iteration":77,"passed_time":0.8063380086,"remaining_time":4.36249538},
{"learn":[0.1465228808],"iteration":78,"passed_time":0.8139774392,"remaining_time":4.337778505},
{"learn":[0.1449001726],"iteration":79,"passed_time":0.8211353378,"remaining_time":4.310960523},
{"learn":[0.1443159052],"iteration":80,"passed_time":0.8287428941,"remaining_time":4.286953983},
{"learn":[0.1437801587],"iteration":81,"passed_time":0.8360694976,"remaining_time":4.261915244},
{"learn":[0.1426952065],"iteration":82,"passed_time":0.8440016724,"remaining_time":4.240345752},
{"learn":[0.1419787555],"iteration":83,"passed_time":0.8518060998,"remaining_time":4.218468304},
{"learn":[0.1404978779],"iteration":84,"passed_time":0.8597299831,"remaining_time":4.197505211},
{"learn":[0.1398410783],"iteration":85,"passed_time":0.8674334541,"remaining_time":4.175784302},
{"learn":[0.1391093528],"iteration":86,"passed_time":0.874876222,"remaining_time":4.153148042},
{"learn":[0.1381880433],"iteration":87,"passed_time":0.8827618144,"remaining_time":4.132930313},
{"learn":[0.1376850301],"iteration":88,"passed_time":0.8906401569,"remaining_time":4.11295623},
{"learn":[0.1364391228],"iteration":89,"passed_time":0.8982425466,"remaining_time":4.091993824},
{"learn":[0.1360513043],"iteration":90,"passed_time":0.9099588958,"remaining_time":4.089815257},
{"learn":[0.1353208375],"iteration":91,"passed_time":0.9413939758,"remaining_time":4.174877632},
{"learn":[0.1345397088],"iteration":92,"passed_time":0.9551308263,"remaining_time":4.179981143},
{"learn":[0.133633059],"iteration":93,"passed_time":0.9629853359,"remaining_time":4.159277089},
{"learn":[0.1321271383],"iteration":94,"passed_time":0.9702374827,"remaining_time":4.136275584},
{"learn":[0.1316928967],"iteration":95,"passed_time":0.9773106746,"remaining_time":4.112849089},
{"learn":[0.1308317603],"iteration":96,"passed_time":0.9847101517,"remaining_time":4.091115373},
{"learn":[0.1298355407],"iteration":97,"passed_time":0.9921115871,"remaining_time":4.069682225},
{"learn":[0.1293325573],"iteration":98,"passed_time":0.9995673548,"remaining_time":4.048752619},
{"learn":[0.1286602006],"iteration":99,"passed_time":1.00658459,"remaining_time":4.026338358},
{"learn":[0.1278696802],"iteration":100,"passed_time":1.013758154,"remaining_time":4.004846571},
{"learn":[0.1267607983],"iteration":101,"passed_time":1.02113984,"remaining_time":3.984447612},
{"learn":[0.1261319305],"iteration":102,"passed_time":1.028573817,"remaining_time":3.964502963},
{"learn":[0.1253695103],"iteration":103,"passed_time":1.035958961,"remaining_time":3.944612966},
{"learn":[0.1241380937],"iteration":104,"passed_time":1.044161255,"remaining_time":3.928035198},
{"learn":[0.1234386853],"iteration":105,"passed_time":1.051259447,"remaining_time":3.907511528},
{"learn":[0.1227487209],"iteration":106,"passed_time":1.059020625,"remaining_time":3.889673884},
{"learn":[0.1214530308],"iteration":107,"passed_time":1.06736075,"remaining_time":3.874124203},
{"learn":[0.1204163182],"iteration":108,"passed_time":1.075570211,"remaining_time":3.858238095},
{"learn":[0.1199568679],"iteration":109,"passed_time":1.083226683,"remaining_time":3.840530966},
{"learn":[0.1191932692],"iteration":110,"passed_time":1.094388918,"remaining_time":3.835290892},
{"learn":[0.1186617167],"iteration":111,"passed_time":1.108587717,"remaining_time":3.840464593},
{"learn":[0.1175078618],"iteration":112,"passed_time":1.122781559,"remaining_time":3.845278436},
{"learn":[0.1165356072],"iteration":113,"passed_time":1.134084666,"remaining_time":3.839970887},
{"learn":[0.1161076902],"iteration":114,"passed_time":1.144051092,"remaining_time":3.83008409},
{"learn":[0.1149286733],"iteration":115,"passed_time":1.156824587,"remaining_time":3.829488287},
{"learn":[0.1142367754],"iteration":116,"passed_time":1.17041619,"remaining_time":3.8313624},
{"learn":[0.1135974197],"iteration":117,"passed_time":1.183128353,"remaining_time":3.830127379},
{"learn":[0.1130989963],"iteration":118,"passed_time":1.193494604,"remaining_time":3.821188605},
{"learn":[0.1125467126],"iteration":119,"passed_time":1.204844419,"remaining_time":3.815340659},
{"learn":[0.1118918957],"iteration":120,"passed_time":1.213350124,"remaining_time":3.800493362},
{"learn":[0.1112888333],"iteration":121,"passed_time":1.226025745,"remaining_time":3.798669932},
{"learn":[0.1109293048],"iteration":122,"passed_time":1.243676892,"remaining_time":3.811920231},
{"learn":[0.1105631461],"iteration":123,"passed_time":1.274866269,"remaining_time":3.865723525},
{"learn":[0.1098165761],"iteration":124,"passed_time":1.290461916,"remaining_time":3.871385747},
{"learn":[0.1090508436],"iteration":125,"passed_time":1.29865921,"remaining_time":3.854750354},
{"learn":[0.1078739994],"iteration":126,"passed_time":1.30715229,"remaining_time":3.839116569},
{"learn":[0.1073255363],"iteration":127,"passed_time":1.318506897,"remaining_time":3.831910669},
{"learn":[0.1069849043],"iteration":128,"passed_time":1.347977974,"remaining_time":3.876742856},
{"learn":[0.1061037705],"iteration":129,"passed_time":1.359525994,"remaining_time":3.869420135},
{"learn":[0.1054740263],"iteration":130,"passed_time":1.369859745,"remaining_time":3.858612565},
{"learn":[0.1051566578],"iteration":131,"passed_time":1.376975103,"remaining_time":3.838839681},
{"learn":[0.1046539565],"iteration":132,"passed_time":1.384233291,"remaining_time":3.819651263},
{"learn":[0.1042394095],"iteration":133,"passed_time":1.391357024,"remaining_time":3.800273663},
{"learn":[0.1034649084],"iteration":134,"passed_time":1.398690002,"remaining_time":3.78164334},
{"learn":[0.1024885152],"iteration":135,"passed_time":1.40656172,"remaining_time":3.764621074},
{"learn":[0.1019606403],"iteration":136,"passed_time":1.413967905,"remaining_time":3.746498903},
{"learn":[0.1016429689],"iteration":137,"passed_time":1.421111763,"remaining_time":3.727843899},
{"learn":[0.100928007],"iteration":138,"passed_time":1.428739902,"remaining_time":3.710612263},
{"learn":[0.1005824587],"iteration":139,"passed_time":1.43652533,"remaining_time":3.693922276},
{"learn":[0.1001001456],"iteration":140,"passed_time":1.444193676,"remaining_time":3.677060495},
{"learn":[0.0996618393],"iteration":141,"passed_time":1.452102102,"remaining_time":3.660933467},
{"learn":[0.09926852911],"iteration":142,"passed_time":1.460117025,"remaining_time":3.645187257},
{"learn":[0.09879470712],"iteration":143,"passed_time":1.467909286,"remaining_time":3.628997956},
{"learn":[0.09791484981],"iteration":144,"passed_time":1.476033832,"remaining_time":3.613738001},
{"learn":[0.09749337799],"iteration":145,"passed_time":1.484141461,"remaining_time":3.598534776},
{"learn":[0.09669018596],"iteration":146,"passed_time":1.492016929,"remaining_time":3.582870584},
{"learn":[0.09631499599],"iteration":147,"passed_time":1.50039847,"remaining_time":3.568515279},
{"learn":[0.09593934305],"iteration":148,"passed_time":1.50773049,"remaining_time":3.551767798},
{"learn":[0.095563844],"iteration":149,"passed_time":1.515500709,"remaining_time":3.536168322},
{"learn":[0.09503942061],"iteration":150,"passed_time":1.522742523,"remaining_time":3.519451262},
{"learn":[0.09455113456],"iteration":151,"passed_time":1.532392747,"remaining_time":3.508372868},
{"learn":[0.09389198553],"iteration":152,"passed_time":1.559307,"remaining_time":3.536467511},
{"learn":[0.09353356228],"iteration":153,"passed_time":1.571886166,"remaining_time":3.531640346},
{"learn":[0.09298694817],"iteration":154,"passed_time":1.582086295,"remaining_time":3.521417883},
{"learn":[0.09274031066],"iteration":155,"passed_time":1.589062156,"remaining_time":3.504085779},
{"learn":[0.09226333312],"iteration":156,"passed_time":1.596191138,"remaining_time":3.48722013},
{"learn":[0.09184964945],"iteration":157,"passed_time":1.603317746,"remaining_time":3.470472589},
{"learn":[0.09131037667],"iteration":158,"passed_time":1.611194922,"remaining_time":3.455455775},
{"learn":[0.09078190659],"iteration":159,"passed_time":1.618281113,"remaining_time":3.438847366},
{"learn":[0.09035631278],"iteration":160,"passed_time":1.625496261,"remaining_time":3.422628773},
{"learn":[0.08973625972],"iteration":161,"passed_time":1.632796073,"remaining_time":3.40669798},
{"learn":[0.08930840573],"iteration":162,"passed_time":1.640113385,"remaining_time":3.390909269},
{"learn":[0.0886324801],"iteration":163,"passed_time":1.648176474,"remaining_time":3.376751801},
{"learn":[0.08835372996],"iteration":164,"passed_time":1.655172543,"remaining_time":3.360501829},
{"learn":[0.08782189633],"iteration":165,"passed_time":1.663426294,"remaining_time":3.346893869},
{"learn":[0.0875131903],"iteration":166,"passed_time":1.671194931,"remaining_time":3.332382706},
{"learn":[0.0872249466],"iteration":167,"passed_time":1.678868569,"remaining_time":3.317764077},
{"learn":[0.08682162901],"iteration":168,"passed_time":1.686366419,"remaining_time":3.302883342},
{"learn":[0.08660983371],"iteration":169,"passed_time":1.694759501,"remaining_time":3.289827268},
{"learn":[0.08630906414],"iteration":170,"passed_time":1.702390057,"remaining_time":3.275358648},
{"learn":[0.08586845928],"iteration":171,"passed_time":1.710200318,"remaining_time":3.261312234},
{"learn":[0.08556943577],"iteration":172,"passed_time":1.727863673,"remaining_time":3.265961972},
{"learn":[0.08528753729],"iteration":173,"passed_time":1.751221915,"remaining_time":3.281024966},
{"learn":[0.08484139954],"iteration":174,"passed_time":1.763590417,"remaining_time":3.275239347},
{"learn":[0.08449475716],"iteration":175,"passed_time":1.770841981,"remaining_time":3.259959101},
{"learn":[0.08423319532],"iteration":176,"passed_time":1.777828716,"remaining_time":3.244286301},
{"learn":[0.08369254577],"iteration":177,"passed_time":1.785021697,"remaining_time":3.229084194},
{"learn":[0.08329256093],"iteration":178,"passed_time":1.792232178,"remaining_time":3.214002957},
{"learn":[0.08303428182],"iteration":179,"passed_time":1.799444826,"remaining_time":3.199013024},
{"learn":[0.0826175531],"iteration":180,"passed_time":1.80638177,"remaining_time":3.18362312},
{"learn":[0.08225369007],"iteration":181,"passed_time":1.81324205,"remaining_time":3.168192153},
{"learn":[0.08194389804],"iteration":182,"passed_time":1.820376824,"remaining_time":3.153330346},
{"learn":[0.08145299207],"iteration":183,"passed_time":1.827367226,"remaining_time":3.138304584},
{"learn":[0.08116698109],"iteration":184,"passed_time":1.834923617,"remaining_time":3.124329401},
{"learn":[0.08065543312],"iteration":185,"passed_time":1.84267992,"remaining_time":3.110760725},
{"learn":[0.08039536117],"iteration":186,"passed_time":1.850218769,"remaining_time":3.09689024},
{"learn":[0.08009612854],"iteration":187,"passed_time":1.858014155,"remaining_time":3.083512853},
{"learn":[0.07984985588],"iteration":188,"passed_time":1.86563242,"remaining_time":3.069903082},
{"learn":[0.07945955755],"iteration":189,"passed_time":1.874732113,"remaining_time":3.058773447},
{"learn":[0.079087778],"iteration":190,"passed_time":1.883945054,"remaining_time":3.04784828},
{"learn":[0.07883148854],"iteration":191,"passed_time":1.894181432,"remaining_time":3.038582714},
{"learn":[0.07830903822],"iteration":192,"passed_time":1.910655103,"remaining_time":3.039228584},
{"learn":[0.07799189139],"iteration":193,"passed_time":1.950793759,"remaining_time":3.077025208},
{"learn":[0.07771122297],"iteration":194,"passed_time":1.97217654,"remaining_time":3.084686383},
{"learn":[0.07716215745],"iteration":195,"passed_time":1.983314109,"remaining_time":3.076160659},
{"learn":[0.07679053361],"iteration":196,"passed_time":1.99702671,"remaining_time":3.071569001},
{"learn":[0.07646596441],"iteration":197,"passed_time":2.01138509,"remaining_time":3.067870187},
{"learn":[0.07582016893],"iteration":198,"passed_time":2.022232998,"remaining_time":3.058754434},
{"learn":[0.07516759739],"iteration":199,"passed_time":2.032576583,"remaining_time":3.048864874},
{"learn":[0.0749079529],"iteration":200,"passed_time":2.042445844,"remaining_time":3.038265211},
{"learn":[0.07459899292],"iteration":201,"passed_time":2.054611642,"remaining_time":3.03106074},
{"learn":[0.07440025491],"iteration":202,"passed_time":2.065683921,"remaining_time":3.02220751},
{"learn":[0.07406327012],"iteration":203,"passed_time":2.076770241,"remaining_time":3.013352899},
{"learn":[0.0738113116],"iteration":204,"passed_time":2.084885496,"remaining_time":3.000201079},
{"learn":[0.07354866623],"iteration":205,"passed_time":2.093307077,"remaining_time":2.987535343},
{"learn":[0.0730324045],"iteration":206,"passed_time":2.102184025,"remaining_time":2.975555166},
{"learn":[0.07275121977],"iteration":207,"passed_time":2.110783645,"remaining_time":2.963215501},
{"learn":[0.07246651931],"iteration":208,"passed_time":2.122468911,"remaining_time":2.95520791},
{"learn":[0.07219070021],"iteration":209,"passed_time":2.144041855,"remaining_time":2.960819704},
{"learn":[0.07187462115],"iteration":210,"passed_time":2.163731336,"remaining_time":2.963594105},
{"learn":[0.07142435287],"iteration":211,"passed_time":2.177924386,"remaining_time":2.958689732},
{"learn":[0.07123195802],"iteration":212,"passed_time":2.185174533,"remaining_time":2.94434315},
{"learn":[0.07095329212],"iteration":213,"passed_time":2.192753298,"remaining_time":2.930502071},
{"learn":[0.07078754211],"iteration":214,"passed_time":2.199698992,"remaining_time":2.91588006},
{"learn":[0.07032349207],"iteration":215,"passed_time":2.206788892,"remaining_time":2.901518729},
{"learn":[0.06989351098],"iteration":216,"passed_time":2.213630089,"remaining_time":2.88690007},
{"learn":[0.06975733244],"iteration":217,"passed_time":2.220499785,"remaining_time":2.87238963},
{"learn":[0.06943279814],"iteration":218,"passed_time":2.227767056,"remaining_time":2.8584591},
{"learn":[0.0690811738],"iteration":219,"passed_time":2.235263365,"remaining_time":2.844880646},
{"learn":[0.06881070339],"iteration":220,"passed_time":2.242497179,"remaining_time":2.83102585},
{"learn":[0.06858815588],"iteration":221,"passed_time":2.250945885,"remaining_time":2.818752054},
{"learn":[0.06833139937],"iteration":222,"passed_time":2.258152533,"remaining_time":2.804969738},
{"learn":[0.06790744502],"iteration":223,"passed_time":2.26630262,"remaining_time":2.792408585},
{"learn":[0.06765430366],"iteration":224,"passed_time":2.274021007,"remaining_time":2.779359009},
{"learn":[0.06741488585],"iteration":225,"passed_time":2.281324903,"remaining_time":2.765854086},
{"learn":[0.06704491241],"iteration":226,"passed_time":2.288551883,"remaining_time":2.752311296},
{"learn":[0.06675420736],"iteration":227,"passed_time":2.296750886,"remaining_time":2.739983513},
{"learn":[0.06646055726],"iteration":228,"passed_time":2.304387317,"remaining_time":2.727026039},
{"learn":[0.06616070614],"iteration":229,"passed_time":2.312123912,"remaining_time":2.714232419},
{"learn":[0.06588760285],"iteration":230,"passed_time":2.345203209,"remaining_time":2.730994213},
{"learn":[0.06564915769],"iteration":231,"passed_time":2.358850853,"remaining_time":2.724879434},
{"learn":[0.06529833676],"iteration":232,"passed_time":2.368654824,"remaining_time":2.714295442},
{"learn":[0.06495265553],"iteration":233,"passed_time":2.37594922,"remaining_time":2.700865352},
{"learn":[0.06476620159],"iteration":234,"passed_time":2.38312516,"remaining_time":2.687353903},
{"learn":[0.06438815169],"iteration":235,"passed_time":2.390940378,"remaining_time":2.674611271},
{"learn":[0.06415499648],"iteration":236,"passed_time":2.397993779,"remaining_time":2.661064827},
{"learn":[0.06385548131],"iteration":237,"passed_time":2.405087054,"remaining_time":2.647616841},
{"learn":[0.06360362064],"iteration":238,"passed_time":2.412085039,"remaining_time":2.634117972},
{"learn":[0.06333056741],"iteration":239,"passed_time":2.419106149,"remaining_time":2.620698328},
{"learn":[0.06297680895],"iteration":240,"passed_time":2.426563208,"remaining_time":2.607800294},
{"learn":[0.06276413702],"iteration":241,"passed_time":2.433964102,"remaining_time":2.594887348},
{"learn":[0.06262542776],"iteration":242,"passed_time":2.441318163,"remaining_time":2.581970238},
{"learn":[0.06239604922],"iteration":243,"passed_time":2.448918303,"remaining_time":2.569356908},
{"learn":[0.0622247306],"iteration":244,"passed_time":2.456288197,"remaining_time":2.556544858},
{"learn":[0.06199318678],"iteration":245,"passed_time":2.464630697,"remaining_time":2.544781289},
{"learn":[0.06166222837],"iteration":246,"passed_time":2.472273503,"remaining_time":2.53232873},
{"learn":[0.06148160059],"iteration":247,"passed_time":2.480022181,"remaining_time":2.520022539},
{"learn":[0.06127184605],"iteration":248,"passed_time":2.487876191,"remaining_time":2.507859132},
{"learn":[0.06106290055],"iteration":249,"passed_time":2.495866865,"remaining_time":2.495866865},
{"learn":[0.06090851167],"iteration":250,"passed_time":2.503742707,"remaining_time":2.483792566},
{"learn":[0.06073206244],"iteration":251,"passed_time":2.521626266,"remaining_time":2.481600453},
{"learn":[0.06046547243],"iteration":252,"passed_time":2.54186332,"remaining_time":2.481581977},
{"learn":[0.06017022774],"iteration":253,"passed_time":2.554494984,"remaining_time":2.47403845},
{"learn":[0.05991434358],"iteration":254,"passed_time":2.562255871,"remaining_time":2.461775249},
{"learn":[0.05966482605],"iteration":255,"passed_time":2.569656348,"remaining_time":2.449203707},
{"learn":[0.0594739785],"iteration":256,"passed_time":2.576952036,"remaining_time":2.436573325},
{"learn":[0.05931987809],"iteration":257,"passed_time":2.584577925,"remaining_time":2.424294023},
{"learn":[0.05925212246],"iteration":258,"passed_time":2.591670325,"remaining_time":2.41155424},
{"learn":[0.05899300728],"iteration":259,"passed_time":2.598547062,"remaining_time":2.398658827},
{"learn":[0.05880179705],"iteration":260,"passed_time":2.606433738,"remaining_time":2.386734342},
{"learn":[0.05848350079],"iteration":261,"passed_time":2.613684301,"remaining_time":2.374262839},
{"learn":[0.05832342873],"iteration":262,"passed_time":2.620702161,"remaining_time":2.361621339},
{"learn":[0.05809078847],"iteration":263,"passed_time":2.627719896,"remaining_time":2.349022331},
{"learn":[0.05789212851],"iteration":264,"passed_time":2.63461405,"remaining_time":2.336355855},
{"learn":[0.05759274355],"iteration":265,"passed_time":2.642143066,"remaining_time":2.324291269},
{"learn":[0.05736906557],"iteration":266,"passed_time":2.649362588,"remaining_time":2.311990573},
{"learn":[0.05717276248],"iteration":267,"passed_time":2.657158599,"remaining_time":2.300226847},
{"learn":[0.05686900251],"iteration":268,"passed_time":2.66478528,"remaining_time":2.288347211},
{"learn":[0.0566451592],"iteration":269,"passed_time":2.673261444,"remaining_time":2.277222712},
{"learn":[0.0563664316],"iteration":270,"passed_time":2.680871,"remaining_time":2.265385458},
{"learn":[0.05628241654],"iteration":271,"passed_time":2.689063545,"remaining_time":2.254067971},
{"learn":[0.05611238327],"iteration":272,"passed_time":2.697074176,"remaining_time":2.242622117},
{"learn":[0.0558619422],"iteration":273,"passed_time":2.706028039,"remaining_time":2.231979331},
{"learn":[0.05559933219],"iteration":274,"passed_time":2.724851413,"remaining_time":2.229423883},
{"learn":[0.05548165355],"iteration":275,"passed_time":2.775393528,"remaining_time":2.252493298},
{"learn":[0.05530836473],"iteration":276,"passed_time":2.787889403,"remaining_time":2.244401938},
{"learn":[0.05487804264],"iteration":277,"passed_time":2.798895808,"remaining_time":2.235089458},
{"learn":[0.05474572204],"iteration":278,"passed_time":2.811220562,"remaining_time":2.226809119},
{"learn":[0.05449222185],"iteration":279,"passed_time":2.821862349,"remaining_time":2.21717756},
{"learn":[0.05429468182],"iteration":280,"passed_time":2.835394578,"remaining_time":2.209791504},
{"learn":[0.05405784582],"iteration":281,"passed_time":2.849009348,"remaining_time":2.202425666},
{"learn":[0.05382495769],"iteration":282,"passed_time":2.860415537,"remaining_time":2.193322161},
{"learn":[0.05353654248],"iteration":283,"passed_time":2.87250992,"remaining_time":2.184725855},
{"learn":[0.05334218993],"iteration":284,"passed_time":2.885385829,"remaining_time":2.176694573},
{"learn":[0.0531791181],"iteration":285,"passed_time":2.894538188,"remaining_time":2.165843259},
{"learn":[0.05306864278],"iteration":286,"passed_time":2.901703545,"remaining_time":2.153529112},
{"learn":[0.05292593992],"iteration":287,"passed_time":2.909552763,"remaining_time":2.141754117},
{"learn":[0.05264324701],"iteration":288,"passed_time":2.91759631,"remaining_time":2.130148171},
{"learn":[0.05247129502],"iteration":289,"passed_time":2.929455365,"remaining_time":2.121329747},
{"learn":[0.05228373152],"iteration":290,"passed_time":2.963607224,"remaining_time":2.128501408},
{"learn":[0.05211974454],"iteration":291,"passed_time":2.973144283,"remaining_time":2.117856202},
{"learn":[0.051955687],"iteration":292,"passed_time":2.98422577,"remaining_time":2.108309674},
{"learn":[0.05176447776],"iteration":293,"passed_time":2.991313629,"remaining_time":2.095954447},
{"learn":[0.05159495172],"iteration":294,"passed_time":2.998612941,"remaining_time":2.083781874},
{"learn":[0.05138738584],"iteration":295,"passed_time":3.005574219,"remaining_time":2.071409259},
{"learn":[0.05123388628],"iteration":296,"passed_time":3.012570912,"remaining_time":2.05909729},
{"learn":[0.0510449791],"iteration":297,"passed_time":3.019608396,"remaining_time":2.046848645},
{"learn":[0.05085330478],"iteration":298,"passed_time":3.026525008,"remaining_time":2.034553601},
{"learn":[0.05073770463],"iteration":299,"passed_time":3.033913402,"remaining_time":2.022608935},
{"learn":[0.05063525825],"iteration":300,"passed_time":3.040901679,"remaining_time":2.010430014},
{"learn":[0.05043923753],"iteration":301,"passed_time":3.047957622,"remaining_time":1.998329831},
{"learn":[0.0501182435],"iteration":302,"passed_time":3.055204477,"remaining_time":1.986387069},
{"learn":[0.04987947993],"iteration":303,"passed_time":3.063028112,"remaining_time":1.974847072},
{"learn":[0.04956606604],"iteration":304,"passed_time":3.070677876,"remaining_time":1.963220281},
{"learn":[0.04936649783],"iteration":305,"passed_time":3.078886003,"remaining_time":1.951973479},
{"learn":[0.04920112369],"iteration":306,"passed_time":3.086697347,"remaining_time":1.940497029},
{"learn":[0.0490200134],"iteration":307,"passed_time":3.094107157,"remaining_time":1.928794072},
{"learn":[0.04884649984],"iteration":308,"passed_time":3.101861836,"remaining_time":1.917332073},
{"learn":[0.04856801976],"iteration":309,"passed_time":3.110331291,"remaining_time":1.906332082},
{"learn":[0.04847819896],"iteration":310,"passed_time":3.117837683,"remaining_time":1.894763094},
{"learn":[0.04834143477],"iteration":311,"passed_time":3.125528779,"remaining_time":1.883331444},
{"learn":[0.04826160909],"iteration":312,"passed_time":3.151804088,"remaining_time":1.883026723},
{"learn":[0.04808890798],"iteration":313,"passed_time":3.167107782,"remaining_time":1.876057476},
{"learn":[0.04790995584],"iteration":314,"passed_time":3.179740113,"remaining_time":1.867466415},
{"learn":[0.04773978173],"iteration":315,"passed_time":3.187116715,"remaining_time":1.85578948},
{"learn":[0.04752709073],"iteration":316,"passed_time":3.194094742,"remaining_time":1.843909583},
{"learn":[0.04737136095],"iteration":317,"passed_time":3.201254766,"remaining_time":1.832164677},
{"learn":[0.04714580051],"iteration":318,"passed_time":3.208128003,"remaining_time":1.820285795},
{"learn":[0.04698236123],"iteration":319,"passed_time":3.215306818,"remaining_time":1.808610085},
{"learn":[0.04677129111],"iteration":320,"passed_time":3.222784586,"remaining_time":1.797129099},
{"learn":[0.04660928352],"iteration":321,"passed_time":3.230047024,"remaining_time":1.785553945},
{"learn":[0.04650707922],"iteration":322,"passed_time":3.237071258,"remaining_time":1.773874962},
{"learn":[0.04629037426],"iteration":323,"passed_time":3.244433736,"remaining_time":1.762408449},
{"learn":[0.046136428],"iteration":324,"passed_time":3.251828338,"remaining_time":1.75098449},
{"learn":[0.04601043362],"iteration":325,"passed_time":3.259682473,"remaining_time":1.739830522},
{"learn":[0.04586142275],"iteration":326,"passed_time":3.266999993,"remaining_time":1.728412841},
{"learn":[0.04568140445],"iteration":327,"passed_time":3.275446075,"remaining_time":1.717611966},
{"learn":[0.04539738241],"iteration":328,"passed_time":3.283886073,"remaining_time":1.706822244},
{"learn":[0.04525810452],"iteration":329,"passed_time":3.291722499,"remaining_time":1.695735833},
{"learn":[0.04506465615],"iteration":330,"passed_time":3.299725589,"remaining_time":1.684754153},
{"learn":[0.04481544525],"iteration":331,"passed_time":3.308633786,"remaining_time":1.674248422},
{"learn":[0.04458327127],"iteration":332,"passed_time":3.316897454,"remaining_time":1.663429054},
{"learn":[0.04446004363],"iteration":333,"passed_time":3.341348757,"remaining_time":1.660670341},
{"learn":[0.04435104575],"iteration":334,"passed_time":3.36039771,"remaining_time":1.65512126},
{"learn":[0.04416153729],"iteration":335,"passed_time":3.373915315,"remaining_time":1.646791999},
{"learn":[0.04405214372],"iteration":336,"passed_time":3.382297564,"remaining_time":1.63594808},
{"learn":[0.04391515743],"iteration":337,"passed_time":3.389971869,"remaining_time":1.624779416},
{"learn":[0.04382820251],"iteration":338,"passed_time":3.397423095,"remaining_time":1.613525423},
{"learn":[0.04372469322],"iteration":339,"passed_time":3.405129024,"remaining_time":1.602413658},
{"learn":[0.04354495636],"iteration":340,"passed_time":3.412480877,"remaining_time":1.591156773},
{"learn":[0.04342001533],"iteration":341,"passed_time":3.420625256,"remaining_time":1.580288861},
{"learn":[0.04311578774],"iteration":342,"passed_time":3.428298561,"remaining_time":1.569221207},
{"learn":[0.04300773907],"iteration":343,"passed_time":3.43703347,"remaining_time":1.558654713},
{"learn":[0.042675585],"iteration":344,"passed_time":3.44488473,"remaining_time":1.547701835},
{"learn":[0.04257564286],"iteration":345,"passed_time":3.45254291,"remaining_time":1.536680948},
{"learn":[0.04238807371],"iteration":346,"passed_time":3.460499793,"remaining_time":1.525811148},
{"learn":[0.04224178038],"iteration":347,"passed_time":3.468742211,"remaining_time":1.515082805},
{"learn":[0.04199693745],"iteration":348,"passed_time":3.477100336,"remaining_time":1.50441877},
{"learn":[0.04185982579],"iteration":349,"passed_time":3.485404545,"remaining_time":1.493744805},
{"learn":[0.04173773724],"iteration":350,"passed_time":3.493418593,"remaining_time":1.482961169},
{"learn":[0.04164947479],"iteration":351,"passed_time":3.501547639,"remaining_time":1.472241621},
{"learn":[0.04154051081],"iteration":352,"passed_time":3.5143328,"remaining_time":1.463475699},
{"learn":[0.04140694737],"iteration":353,"passed_time":3.539812707,"remaining_time":1.459922755},
{"learn":[0.04120211705],"iteration":354,"passed_time":3.579909406,"remaining_time":1.462216518},
{"learn":[0.04097118598],"iteration":355,"passed_time":3.589654419,"remaining_time":1.451995046},
{"learn":[0.0408456092],"iteration":356,"passed_time":3.600256791,"remaining_time":1.442119667},
{"learn":[0.04067990651],"iteration":357,"passed_time":3.612866497,"remaining_time":1.433036432},
{"learn":[0.04053037867],"iteration":358,"passed_time":3.623083626,"remaining_time":1.422993848},
{"learn":[0.04040879739],"iteration":359,"passed_time":3.633277131,"remaining_time":1.412941106},
{"learn":[0.04033247155],"iteration":360,"passed_time":3.645443846,"remaining_time":1.403647353},
{"learn":[0.04019575378],"iteration":361,"passed_time":3.657859348,"remaining_time":1.394432569},
{"learn":[0.04006416061],"iteration":362,"passed_time":3.668079102,"remaining_time":1.384371452},
{"learn":[0.03991595582],"iteration":363,"passed_time":3.679985364,"remaining_time":1.374939587},
{"learn":[0.03978308624],"iteration":364,"passed_time":3.6898535,"remaining_time":1.364740336},
{"learn":[0.03967191285],"iteration":365,"passed_time":3.699603555,"remaining_time":1.354499662},
{"learn":[0.03958492206],"iteration":366,"passed_time":3.708974118,"remaining_time":1.344124135},
{"learn":[0.03943036431],"iteration":367,"passed_time":3.717176412,"remaining_time":1.333335017},
{"learn":[0.03934950458],"iteration":368,"passed_time":3.725418873,"remaining_time":1.32257418},
{"learn":[0.03924289427],"iteration":369,"passed_time":3.732936181,"remaining_time":1.311572172},
{"learn":[0.03917828457],"iteration":370,"passed_time":3.767937439,"remaining_time":1.310145363},
{"learn":[0.03909036218],"iteration":371,"passed_time":3.781093385,"remaining_time":1.30102138},
{"learn":[0.03891528934],"iteration":372,"passed_time":3.790149829,"remaining_time":1.290479969},
{"learn":[0.0388302849],"iteration":373,"passed_time":3.797564097,"remaining_time":1.279393252},
{"learn":[0.03864153062],"iteration":374,"passed_time":3.804977324,"remaining_time":1.268325775},
{"learn":[0.0385065855],"iteration":375,"passed_time":3.812296969,"remaining_time":1.257246873},
{"learn":[0.03835111992],"iteration":376,"passed_time":3.819795653,"remaining_time":1.246246327},
{"learn":[0.03825919207],"iteration":377,"passed_time":3.82712684,"remaining_time":1.23521025},
{"learn":[0.03812642991],"iteration":378,"passed_time":3.834342779,"remaining_time":1.224156929},
{"learn":[0.03800552106],"iteration":379,"passed_time":3.841292432,"remaining_time":1.213039715},
{"learn":[0.03784839623],"iteration":380,"passed_time":3.848660951,"remaining_time":1.202075205},
{"learn":[0.03771226042],"iteration":381,"passed_time":3.856415546,"remaining_time":1.191248781},
{"learn":[0.03760026217],"iteration":382,"passed_time":3.864415136,"remaining_time":1.18051324},
{"learn":[0.03743201305],"iteration":383,"passed_time":3.872304853,"remaining_time":1.169758758},
{"learn":[0.03734612038],"iteration":384,"passed_time":3.880138239,"remaining_time":1.159002331},
{"learn":[0.03719969512],"iteration":385,"passed_time":3.887721337,"remaining_time":1.148187131},
{"learn":[0.03698807671],"iteration":386,"passed_time":3.895443974,"remaining_time":1.137429378},
{"learn":[0.03683161574],"iteration":387,"passed_time":3.903455106,"remaining_time":1.126770546},
{"learn":[0.03673639039],"iteration":388,"passed_time":3.911180618,"remaining_time":1.116043827},
{"learn":[0.03658161879],"iteration":389,"passed_time":3.918915963,"remaining_time":1.105335272},
{"learn":[0.03649512933],"iteration":390,"passed_time":3.958410174,"remaining_time":1.103495419},
{"learn":[0.03639665504],"iteration":391,"passed_time":3.978047073,"remaining_time":1.095992561},
{"learn":[0.03628806097],"iteration":392,"passed_time":3.987994749,"remaining_time":1.085789919},
{"learn":[0.03621690747],"iteration":393,"passed_time":3.997639015,"remaining_time":1.075506943},
{"learn":[0.03609337203],"iteration":394,"passed_time":4.005598314,"remaining_time":1.064779299},
{"learn":[0.0359445097],"iteration":395,"passed_time":4.014763964,"remaining_time":1.054382455},
{"learn":[0.03586740662],"iteration":396,"passed_time":4.022491935,"remaining_time":1.043618814},
{"learn":[0.03576143689],"iteration":397,"passed_time":4.031788957,"remaining_time":1.033272547},
{"learn":[0.03561803455],"iteration":398,"passed_time":4.039276266,"remaining_time":1.022473441},
{"learn":[0.0354659755],"iteration":399,"passed_time":4.048594247,"remaining_time":1.012148562},
{"learn":[0.03526150903],"iteration":400,"passed_time":4.056365258,"remaining_time":1.001446784},
{"learn":[0.03511164988],"iteration":401,"passed_time":4.06650343,"remaining_time":0.9913366571},
{"learn":[0.03499265854],"iteration":402,"passed_time":4.074595185,"remaining_time":0.9807338287},
{"learn":[0.03491594755],"iteration":403,"passed_time":4.08377371,"remaining_time":0.9704016737},
{"learn":[0.03482210241],"iteration":404,"passed_time":4.093963756,"remaining_time":0.9603124861},
{"learn":[0.03474838163],"iteration":405,"passed_time":4.102806038,"remaining_time":0.9499107576},
{"learn":[0.03450683315],"iteration":406,"passed_time":4.112227433,"remaining_time":0.9396490203},
{"learn":[0.03442462835],"iteration":407,"passed_time":4.120349771,"remaining_time":0.9290984777},
{"learn":[0.03436020378],"iteration":408,"passed_time":4.134801899,"remaining_time":0.9199681486},
{"learn":[0.0342624357],"iteration":409,"passed_time":4.164428473,"remaining_time":0.9141428355},
{"learn":[0.03418968896],"iteration":410,"passed_time":4.17484464,"remaining_time":0.9040417833},
{"learn":[0.03404669949],"iteration":411,"passed_time":4.186165372,"remaining_time":0.8941324095},
{"learn":[0.03395058101],"iteration":412,"passed_time":4.193137358,"remaining_time":0.8833001213},
{"learn":[0.03372700051],"iteration":413,"passed_time":4.200361422,"remaining_time":0.872538846},
{"learn":[0.03364250229],"iteration":414,"passed_time":4.207615693,"remaining_time":0.8618008046},
{"learn":[0.03357249245],"iteration":415,"passed_time":4.214561054,"remaining_time":0.851017136},
{"learn":[0.03349099295],"iteration":416,"passed_time":4.221702787,"remaining_time":0.8402909623},
{"learn":[0.03336822173],"iteration":417,"passed_time":4.229147804,"remaining_time":0.8296414353},
{"learn":[0.03327467825],"iteration":418,"passed_time":4.237156686,"remaining_time":0.819116209},
{"learn":[0.03317595104],"iteration":419,"passed_time":4.244546497,"remaining_time":0.808485047},
{"learn":[0.03306314153],"iteration":420,"passed_time":4.252315175,"remaining_time":0.7979403772},
{"learn":[0.03286727331],"iteration":421,"passed_time":4.259894232,"remaining_time":0.7873738153},
{"learn":[0.03275178478],"iteration":422,"passed_time":4.267754824,"remaining_time":0.7768726276},
{"learn":[0.03255797519],"iteration":423,"passed_time":4.275181384,"remaining_time":0.7663060972},
{"learn":[0.03244845566],"iteration":424,"passed_time":4.283487593,"remaining_time":0.7559095753},
{"learn":[0.03233708071],"iteration":425,"passed_time":4.291316395,"remaining_time":0.7454399372},
{"learn":[0.03224921996],"iteration":426,"passed_time":4.299005492,"remaining_time":0.7349587843},
{"learn":[0.03217005156],"iteration":427,"passed_time":4.306474259,"remaining_time":0.7244536137},
{"learn":[0.03202119701],"iteration":428,"passed_time":4.317673577,"remaining_time":0.7145800092},
{"learn":[0.03186096261],"iteration":429,"passed_time":4.329880416,"remaining_time":0.7048642538},
{"learn":[0.0317854542],"iteration":430,"passed_time":4.383328598,"remaining_time":0.7017393811},
{"learn":[0.03162416073],"iteration":431,"passed_time":4.395943846,"remaining_time":0.6919541239},
{"learn":[0.03149940642],"iteration":432,"passed_time":4.407748443,"remaining_time":0.6820303596},
{"learn":[0.03145135571],"iteration":433,"passed_time":4.419384044,"remaining_time":0.6720722279},
{"learn":[0.03135310056],"iteration":434,"passed_time":4.431381721,"remaining_time":0.662160487},
{"learn":[0.03128099495],"iteration":435,"passed_time":4.44308932,"remaining_time":0.6521965974},
{"learn":[0.03111641301],"iteration":436,"passed_time":4.453299324,"remaining_time":0.6420088271},
{"learn":[0.03105080166],"iteration":437,"passed_time":4.465458165,"remaining_time":0.6320968178},
{"learn":[0.03092654631],"iteration":438,"passed_time":4.477387718,"remaining_time":0.6221427125},
{"learn":[0.03083113621],"iteration":439,"passed_time":4.487065024,"remaining_time":0.6118725033},
{"learn":[0.03073502491],"iteration":440,"passed_time":4.494917451,"remaining_time":0.6013608381},
{"learn":[0.03063962921],"iteration":441,"passed_time":4.502430301,"remaining_time":0.5908166458},
{"learn":[0.030533031],"iteration":442,"passed_time":4.510089814,"remaining_time":0.58030501},
{"learn":[0.0304662722],"iteration":443,"passed_time":4.518347358,"remaining_time":0.5698816487},
{"learn":[0.03035750124],"iteration":444,"passed_time":4.52596933,"remaining_time":0.5593894678},
{"learn":[0.03025084488],"iteration":445,"passed_time":4.533288059,"remaining_time":0.5488734421},
{"learn":[0.03018023264],"iteration":446,"passed_time":4.54597368,"remaining_time":0.539008065},
{"learn":[0.03005022449],"iteration":447,"passed_time":4.574282906,"remaining_time":0.5309435516},
{"learn":[0.02997807217],"iteration":448,"passed_time":4.588084255,"remaining_time":0.5211409733},
{"learn":[0.02993199654],"iteration":449,"passed_time":4.595579147,"remaining_time":0.5106199052},
{"learn":[0.02989371494],"iteration":450,"passed_time":4.604893794,"remaining_time":0.5003099688},
{"learn":[0.0298516107],"iteration":451,"passed_time":4.612168149,"remaining_time":0.489787768},
{"learn":[0.0297457849],"iteration":452,"passed_time":4.619792413,"remaining_time":0.4793162106},
{"learn":[0.02966323588],"iteration":453,"passed_time":4.626667026,"remaining_time":0.4687812405},
{"learn":[0.02958295411],"iteration":454,"passed_time":4.633745634,"remaining_time":0.4582825353},
{"learn":[0.02945499583],"iteration":455,"passed_time":4.641355107,"remaining_time":0.4478500542},
{"learn":[0.0293761777],"iteration":456,"passed_time":4.648501048,"remaining_time":0.437386313},
{"learn":[0.02926381019],"iteration":457,"passed_time":4.656212602,"remaining_time":0.4269889286},
{"learn":[0.02912972066],"iteration":458,"passed_time":4.663858282,"remaining_time":0.4165973629},
{"learn":[0.02907574594],"iteration":459,"passed_time":4.672095076,"remaining_time":0.4062691371},
{"learn":[0.02898630424],"iteration":460,"passed_time":4.679551302,"remaining_time":0.3958839496},
{"learn":[0.02885111929],"iteration":461,"passed_time":4.687785804,"remaining_time":0.3855754558},
{"learn":[0.02873907801],"iteration":462,"passed_time":4.695715729,"remaining_time":0.3752515809},
{"learn":[0.0286619711],"iteration":463,"passed_time":4.703799568,"remaining_time":0.3649499664},
{"learn":[0.02842772402],"iteration":464,"passed_time":4.712063611,"remaining_time":0.3546714546},
{"learn":[0.02837671158],"iteration":465,"passed_time":4.719715708,"remaining_time":0.34435694},
{"learn":[0.02832966929],"iteration":466,"passed_time":4.727445803,"remaining_time":0.3340593394},
{"learn":[0.02825852185],"iteration":467,"passed_time":4.734781657,"remaining_time":0.3237457543},
{"learn":[0.02820435979],"iteration":468,"passed_time":4.751669777,"remaining_time":0.3140762539},
{"learn":[0.02810063128],"iteration":469,"passed_time":4.776344701,"remaining_time":0.304873066},
{"learn":[0.02799294001],"iteration":470,"passed_time":4.788885075,"remaining_time":0.2948570428},
{"learn":[0.02787496038],"iteration":471,"passed_time":4.796384342,"remaining_time":0.2845312745},
{"learn":[0.02782865799],"iteration":472,"passed_time":4.803597031,"remaining_time":0.274201099},
{"learn":[0.02770490696],"iteration":473,"passed_time":4.810685431,"remaining_time":0.2638772599},
{"learn":[0.02760138492],"iteration":474,"passed_time":4.818030118,"remaining_time":0.2535805325},
{"learn":[0.02755039134],"iteration":475,"passed_time":4.824961729,"remaining_time":0.2432753813},
{"learn":[0.02751893421],"iteration":476,"passed_time":4.832821572,"remaining_time":0.2330291324},
{"learn":[0.02746562354],"iteration":477,"passed_time":4.83994093,"remaining_time":0.2227587876},
{"learn":[0.02738062085],"iteration":478,"passed_time":4.847089745,"remaining_time":0.2125028907},
{"learn":[0.0273037044],"iteration":479,"passed_time":4.854154312,"remaining_time":0.2022564297},
{"learn":[0.02726074253],"iteration":480,"passed_time":4.861236504,"remaining_time":0.1920238952},
{"learn":[0.02716703847],"iteration":481,"passed_time":4.868839727,"remaining_time":0.1818238902},
{"learn":[0.02703424026],"iteration":482,"passed_time":4.883225815,"remaining_time":0.1718733724},
{"learn":[0.02693862659],"iteration":483,"passed_time":4.891093199,"remaining_time":0.1616890314},
{"learn":[0.02687732806],"iteration":484,"passed_time":4.899004624,"remaining_time":0.1515156069},
{"learn":[0.02682020401],"iteration":485,"passed_time":4.906683679,"remaining_time":0.1413447973},
{"learn":[0.02674431539],"iteration":486,"passed_time":4.914520647,"remaining_time":0.1311884362},
{"learn":[0.02669830226],"iteration":487,"passed_time":4.922830481,"remaining_time":0.1210532086},
{"learn":[0.02664388877],"iteration":488,"passed_time":4.931395102,"remaining_time":0.1109311782},
{"learn":[0.02656069296],"iteration":489,"passed_time":4.939208154,"remaining_time":0.1008001664},
{"learn":[0.02647122494],"iteration":490,"passed_time":4.969026141,"remaining_time":0.09108194556},
{"learn":[0.02641072559],"iteration":491,"passed_time":4.985309399,"remaining_time":0.08106194145},
{"learn":[0.0263374207],"iteration":492,"passed_time":4.994351427,"remaining_time":0.07091371194},
{"learn":[0.02629301529],"iteration":493,"passed_time":5.001807403,"remaining_time":0.0607506972},
{"learn":[0.02625647786],"iteration":494,"passed_time":5.009299961,"remaining_time":0.05059898951},
{"learn":[0.02619401565],"iteration":495,"passed_time":5.01661769,"remaining_time":0.04045659428},
{"learn":[0.02612144335],"iteration":496,"passed_time":5.023836296,"remaining_time":0.03032496758},
{"learn":[0.02603815156],"iteration":497,"passed_time":5.031281814,"remaining_time":0.02020595106},
{"learn":[0.02600504536],"iteration":498,"passed_time":5.03824505,"remaining_time":0.01009668347},
{"learn":[0.02587210599],"iteration":499,"passed_time":5.046092518,"remaining_time":0}
]}